Metadata-Version: 2.1
Name: mypoems
Version: 0.1.0
Summary: My favorite and least favorite poems
Author: Your Name
License: MIT
License-File: LICENSE
